hao/__init__.py
hao/arango.py
hao/args.py
hao/asyncs.py
hao/charsets.py
hao/cli.py
hao/config.py
hao/currencies.py
hao/dates.py
hao/db.py
hao/decorators.py
hao/dicts.py
hao/english.py
hao/enums.py
hao/envs.py
hao/es.py
hao/exceptions.py
hao/exits.py
hao/feishu.py
hao/files.py
hao/gits.py
hao/hf.py
hao/invoker.py
hao/jsons.py
hao/kafka.py
hao/lists.py
hao/logs.py
hao/meters.py
hao/modules.py
hao/mongo.py
hao/mysql.py
hao/namespaces.py
hao/nations.py
hao/networks.py
hao/o2.py
hao/oss.py
hao/paths.py
hao/pg.py
hao/places.py
hao/rabbit.py
hao/redis.py
hao/regexes.py
hao/rmq.py
hao/s3.py
hao/singleton.py
hao/slacks.py
hao/spinner.py
hao/sqlite.py
hao/stopwatch.py
hao/strings.py
hao/systems.py
hao/threads.py
hao/uuid.py
hao/versions.py
hao/vs.py
hao-3.8.17.dist-info/entry_points.txt
hao-3.8.17.dist-info/LICENSE
hao-3.8.17.dist-info/WHEEL
hao-3.8.17.dist-info/METADATA
hao-3.8.17.dist-info/RECORD
