Metadata-Version: 2.3
Name: hao
Version: 3.8.17
Summary: conf, logs, namespace, etc
Home-page: https://github.com/orctom/hao
License: Apache-2.0
Author: orctom
Author-email: orctom <orctom@gmail.com>
Requires-Python: >=3.8
Classifier: Intended Audience :: Developers
Requires-Dist: PyYAML
Requires-Dist: requests
Requires-Dist: charset-normalizer
Requires-Dist: dateparser
Requires-Dist: regex
Requires-Dist: tqdm
Requires-Dist: decorator
Requires-Dist: urllib3>=1.26.5
Requires-Dist: minio
Requires-Dist: ruff ; extra == "dev"
Requires-Dist: pytest>=7.2.0 ; extra == "dev"
Requires-Dist: elasticsearch<8 ; extra == "dev"
Requires-Dist: pymongo ; extra == "dev"
Requires-Dist: kafka-python ; extra == "dev"
Requires-Dist: pymysql ; extra == "dev"
Requires-Dist: dbutils>=3.0.0 ; extra == "dev"
Requires-Dist: psycopg[binary] ; extra == "dev"
Requires-Dist: kombu ; extra == "dev"
Requires-Dist: redis ; extra == "dev"
Requires-Dist: sqlalchemy ; extra == "dev"
Requires-Dist: jieba ; extra == "dev"
Requires-Dist: elasticsearch<8 ; extra == "es"
Requires-Dist: kafka-python ; extra == "kafka"
Requires-Dist: pymongo ; extra == "mongo"
Requires-Dist: pymysql ; extra == "mysql"
Requires-Dist: dbutils>=3.0.0 ; extra == "mysql"
Requires-Dist: psycopg[binary] ; extra == "pg"
Requires-Dist: dbutils>=3.0.0 ; extra == "pg"
Requires-Dist: kombu ; extra == "rabbit"
Requires-Dist: redis ; extra == "redis"
Requires-Dist: sqlalchemy ; extra == "sql"
Requires-Dist: psutil ; extra == "sys"
Requires-Dist: nvidia-ml-py ; extra == "sys"
Project-URL: homepage, https://github.com/orctom/hao
Project-URL: repository, https://github.com/orctom/hao
Provides-Extra: dev
Provides-Extra: es
Provides-Extra: kafka
Provides-Extra: mongo
Provides-Extra: mysql
Provides-Extra: pg
Provides-Extra: rabbit
Provides-Extra: redis
Provides-Extra: sql
Provides-Extra: sys
